config/__init__.py
config/asgi.py
config/settings.py
config/urls.py
config/wsgi.py
niceauth/__init__.py
niceauth/admin.py
niceauth/apps.py
niceauth/models.py
niceauth/serializers.py
niceauth/urls.py
niceauth/views.py
niceauth/locale/ko/LC_MESSAGES/django.po
niceauth/migrations/0001_initial.py
niceauth/migrations/0002_niceauthrequest_authtype_niceauthrequest_popupyn_and_more.py
niceauth/migrations/0003_rename_result_data_niceauthresult_result.py
niceauth/migrations/0004_niceauthrequest_is_verified_and_more.py
niceauth/migrations/0005_niceauthresult_authtype_niceauthresult_birthdate_and_more.py
niceauth/migrations/0006_niceauthresult_redirect_url_and_more.py
niceauth/migrations/__init__.py
django_nice_auth-0.1.11.dist-info/LICENSE
django_nice_auth-0.1.11.dist-info/METADATA
django_nice_auth-0.1.11.dist-info/WHEEL
django_nice_auth-0.1.11.dist-info/top_level.txt
django_nice_auth-0.1.11.dist-info/RECORD
