Metadata-Version: 2.1
Name: django-nice-auth
Version: 0.1.11
Summary: A Django app for NICE authentication
Home-page: https://github.com/RUNNERS-IM/django-nice-auth
Author: RUNNERS
Author-email: dev@runners.im
License: UNKNOWN
Platform: UNKNOWN
Classifier: Framework :: Django
Classifier: Programming Language :: Python :: 3
Classifier: License :: OSI Approved :: MIT License
Classifier: Operating System :: OS Independent
Requires-Python: >=3.6
Requires-Dist: django>=3.0
Requires-Dist: requests
Requires-Dist: pycryptodome
Requires-Dist: nice-auth>=0.1.5
Requires-Dist: djangorestframework
Requires-Dist: drf-yasg
